serialise/__init__.py
serialise/_lib.py
serialise-0.0.0.dist-info/LICENSE
serialise-0.0.0.dist-info/METADATA
serialise-0.0.0.dist-info/WHEEL
serialise-0.0.0.dist-info/entry_points.txt
serialise-0.0.0.dist-info/top_level.txt
serialise-0.0.0.dist-info/RECORD
