Metadata-Version: 2.1
Name: serialise
Version: 0.0.0
Summary: A project to allow serialising and deserialising python objects
Author: RJ_Infinity
License: MIT License
Project-URL: Homepage, https://github.com/RJ-Infinity/serialise
Project-URL: Documentation, https://github.com/RJ-Infinity/serialise
Project-URL: Repository, https://github.com/RJ-Infinity/serialise
Project-URL: Issues, https://github.com/RJ-Infinity/serialise/issues
Keywords: serialiser,serialisation,deserialiser,deserialisation,binary,format,saving
Classifier: Programming Language :: Python :: 3
Classifier: License :: OSI Approved :: MIT License
Classifier: Operating System :: OS Independent
Requires-Python: >=3.12
License-File: LICENSE
